openfdcm.cpython-313-i386-linux-musl.so
libz.so.1.3.1
libopenfdcm_matching.so
libz.so.1
libz.so
openfdcm.libs/libopenfdcm_matching-e5fd00d3.so
openfdcm.libs/libstdc++-d2a021ba.so.6.0.32
openfdcm.libs/libgcc_s-f3fb5a36.so.1
openfdcm-0.10.0.dist-info/RECORD
openfdcm-0.10.0.dist-info/WHEEL
openfdcm-0.10.0.dist-info/LICENSE
openfdcm-0.10.0.dist-info/top_level.txt
openfdcm-0.10.0.dist-info/METADATA
